pyexe/__init__.py
pyexe/git.py
pyexe/local.py
pyexe/main.py
pyexe/remote.py
pyexe-0.1.3.dist-info/LICENSE
pyexe-0.1.3.dist-info/METADATA
pyexe-0.1.3.dist-info/WHEEL
pyexe-0.1.3.dist-info/top_level.txt
pyexe-0.1.3.dist-info/RECORD
