Metadata-Version: 2.1
Name: pyexe
Version: 0.1.3
Summary: Python package to execute local and remote commands
Home-page: https://github.com/shivampip/pyexe
Author: You
Author-email: shivam301296@gmail.com
License: Apache License 2.0
Platform: UNKNOWN
Requires-Dist: fancybox
Requires-Dist: termcolor
Requires-Dist: fabric
